[{"stackHeaders":{"api_key":"bltbaf6b339f605c4db"},"urlPath":"/assets/bltf0d763dd04359d75","uid":"bltf0d763dd04359d75","content_type":"image/jpeg","file_size":"1895043","tags":[],"filename":"food_blog.jpg","url":"https://images.contentstack.io/v3/assets/bltbaf6b339f605c4db/bltf0d763dd04359d75/5f96d4611a81c1644e995bb9/food_blog.jpg","ACL":{},"is_dir":false,"parent_uid":null,"_version":1,"title":"food_blog.jpg","publish_details":[{"environment":"bltdfbe17c7b77e5b71","locale":"en-us","time":"2020-10-26T14:07:14.089Z","user":"blt1d7a52a45d858cdb","version":1}]}]